OpencvZhongwenWendang/README.md
OpencvZhongwenWendang/__init__.py
OpencvZhongwenWendang/__main__.py
OpencvZhongwenWendang/file.epub
OpencvZhongwenWendang/index.html
OpencvZhongwenWendang/css/__init__.py
OpencvZhongwenWendang/css/annotations.css
OpencvZhongwenWendang/css/main.css
OpencvZhongwenWendang/css/normalize.css
OpencvZhongwenWendang/css/popup.css
OpencvZhongwenWendang/font/__init__.py
OpencvZhongwenWendang/font/fontello.eot
OpencvZhongwenWendang/font/fontello.svg
OpencvZhongwenWendang/font/fontello.ttf
OpencvZhongwenWendang/font/fontello.woff
OpencvZhongwenWendang/img/__init__.py
OpencvZhongwenWendang/img/annotator-glyph-sprite.png
OpencvZhongwenWendang/img/annotator-icon-sprite.png
OpencvZhongwenWendang/img/apple-touch-icon.png
OpencvZhongwenWendang/img/cancelfullscreen.png
OpencvZhongwenWendang/img/close.png
OpencvZhongwenWendang/img/fullscreen.png
OpencvZhongwenWendang/img/loader.gif
OpencvZhongwenWendang/img/menu-icon.png
OpencvZhongwenWendang/img/save.png
OpencvZhongwenWendang/img/saved.png
OpencvZhongwenWendang/img/settings-s.png
OpencvZhongwenWendang/img/settings.png
OpencvZhongwenWendang/img/star.png
OpencvZhongwenWendang/js/__init__.py
OpencvZhongwenWendang/js/epub.js
OpencvZhongwenWendang/js/epub.min.js
OpencvZhongwenWendang/js/epub.min.map
OpencvZhongwenWendang/js/hooks.min.js
OpencvZhongwenWendang/js/hooks.min.map
OpencvZhongwenWendang/js/reader.js
OpencvZhongwenWendang/js/reader.js.map
OpencvZhongwenWendang/js/reader.min.js
OpencvZhongwenWendang/js/reader.min.map
OpencvZhongwenWendang/js/hooks/__init__.py
OpencvZhongwenWendang/js/hooks/extensions/__init__.py
OpencvZhongwenWendang/js/hooks/extensions/highlight.js
OpencvZhongwenWendang/js/libs/__init__.py
OpencvZhongwenWendang/js/libs/jquery.min.js
OpencvZhongwenWendang/js/libs/localforage.min.js
OpencvZhongwenWendang/js/libs/screenfull.js
OpencvZhongwenWendang/js/libs/screenfull.min.js
OpencvZhongwenWendang/js/libs/zip.min.js
OpencvZhongwenWendang/js/plugins/__init__.py
opencv_zhongwen_wendang-2024.3.2.0.dist-info/METADATA
opencv_zhongwen_wendang-2024.3.2.0.dist-info/WHEEL
opencv_zhongwen_wendang-2024.3.2.0.dist-info/entry_points.txt
opencv_zhongwen_wendang-2024.3.2.0.dist-info/top_level.txt
opencv_zhongwen_wendang-2024.3.2.0.dist-info/RECORD
